aliyunsdkimm/__init__.py
aliyunsdkimm/endpoint.py
aliyunsdkimm/request/__init__.py
aliyunsdkimm/request/v20200930/AddImageMosaicRequest.py
aliyunsdkimm/request/v20200930/AddStoryFilesRequest.py
aliyunsdkimm/request/v20200930/AttachOSSBucketRequest.py
aliyunsdkimm/request/v20200930/BatchDeleteFileMetaRequest.py
aliyunsdkimm/request/v20200930/BatchGetFigureClusterRequest.py
aliyunsdkimm/request/v20200930/BatchGetFileMetaRequest.py
aliyunsdkimm/request/v20200930/BatchIndexFileMetaRequest.py
aliyunsdkimm/request/v20200930/BatchUpdateFileMetaRequest.py
aliyunsdkimm/request/v20200930/CompareImageFacesRequest.py
aliyunsdkimm/request/v20200930/CreateArchiveFileInspectionTaskRequest.py
aliyunsdkimm/request/v20200930/CreateBatchRequest.py
aliyunsdkimm/request/v20200930/CreateBindingRequest.py
aliyunsdkimm/request/v20200930/CreateCompressPointCloudTaskRequest.py
aliyunsdkimm/request/v20200930/CreateCustomizedStoryRequest.py
aliyunsdkimm/request/v20200930/CreateDatasetRequest.py
aliyunsdkimm/request/v20200930/CreateFacesSearchingTaskRequest.py
aliyunsdkimm/request/v20200930/CreateFigureClusteringTaskRequest.py
aliyunsdkimm/request/v20200930/CreateFigureClustersMergingTaskRequest.py
aliyunsdkimm/request/v20200930/CreateFileCompressionTaskRequest.py
aliyunsdkimm/request/v20200930/CreateFileUncompressionTaskRequest.py
aliyunsdkimm/request/v20200930/CreateImageModerationTaskRequest.py
aliyunsdkimm/request/v20200930/CreateImageSplicingTaskRequest.py
aliyunsdkimm/request/v20200930/CreateImageToPDFTaskRequest.py
aliyunsdkimm/request/v20200930/CreateLocationDateClusteringTaskRequest.py
aliyunsdkimm/request/v20200930/CreateMediaConvertTaskRequest.py
aliyunsdkimm/request/v20200930/CreateOfficeConversionTaskRequest.py
aliyunsdkimm/request/v20200930/CreateProjectRequest.py
aliyunsdkimm/request/v20200930/CreateSimilarImageClusteringTaskRequest.py
aliyunsdkimm/request/v20200930/CreateStoryRequest.py
aliyunsdkimm/request/v20200930/CreateTriggerRequest.py
aliyun_python_sdk_imm-2.1.17.dist-info/LICENSE
aliyun_python_sdk_imm-2.1.17.dist-info/METADATA
aliyun_python_sdk_imm-2.1.17.dist-info/WHEEL
aliyun_python_sdk_imm-2.1.17.dist-info/top_level.txt
aliyun_python_sdk_imm-2.1.17.dist-info/RECORD
